<?xml version="1.0" encoding="UTF-8"?><record_update>
    <sys_choice action="DELETE" field="u_what_needed" table="x_58872_needit_needit" version="3">
        <sys_choice_set action="DELETE">
            <element>u_what_needed</element>
            <name>x_58872_needit_needit</name>
            <sys_class_name/>
            <sys_created_by/>
            <sys_created_on/>
            <sys_id/>
            <sys_mod_count/>
            <sys_name/>
            <sys_package/>
            <sys_policy/>
            <sys_scope/>
            <sys_update_name/>
            <sys_updated_by/>
            <sys_updated_on>2020-01-22 13:37:33</sys_updated_on>
        </sys_choice_set>
    </sys_choice>
    <sys_update_version action="INSERT_OR_UPDATE">
        <action>DELETE</action>
        <application/>
        <file_path/>
        <instance_id>5d19cfd7db3d889491232f17d49619aa</instance_id>
        <instance_name>dev96486</instance_name>
        <name>sys_choice_x_58872_needit_needit_u_what_needed</name>
        <payload><![CDATA[<?xml version="1.0" encoding="UTF-8"?><record_update><sys_choice action="DELETE" field="u_what_needed" table="x_58872_needit_needit" version="3"><sys_choice_set action="DELETE"><element>u_what_needed</element><name>x_58872_needit_needit</name><sys_class_name/><sys_created_by/><sys_created_on/><sys_id/><sys_mod_count/><sys_name/><sys_package/><sys_policy/><sys_scope/><sys_update_name/><sys_updated_by/><sys_updated_on>2020-01-22 13:37:33</sys_updated_on></sys_choice_set></sys_choice></record_update>]]></payload>
        <payload_hash>-429457270</payload_hash>
        <record_name>x_58872_needit_needit.u_what_needed</record_name>
        <reverted_from/>
        <source>f4a6b1f42f624010b634811df699b6ec</source>
        <source_table>sys_update_set</source_table>
        <state>previous</state>
        <sys_created_by>admin</sys_created_by>
        <sys_created_on>2020-01-22 13:37:33</sys_created_on>
        <sys_id>3456ae342f264010b634811df699b610</sys_id>
        <sys_mod_count>0</sys_mod_count>
        <sys_recorded_at>16fcd78f3cd0000001</sys_recorded_at>
        <sys_updated_by>admin</sys_updated_by>
        <sys_updated_on>2020-01-22 13:37:33</sys_updated_on>
        <type>Choice list</type>
        <update_guid>bc56ae34af2640108adcd29a1a31970f</update_guid>
        <update_guid_history>bc56ae34af2640108adcd29a1a31970f:-429457270,7856ae3494264010d4115f83cb0b7b0c:1264701252,f456ae341426401059e635099d2ed809:-1001554480,7456ae34cf2640101f046b98c8f3a306:1291032590,f056ae34fd2640102ce71a511abdd703:1977964177,7056ae34b32640101ee9a2c56ecc1200:-1752887133,fc566e348a264010713447f0172bd7fc:103642638,7c566e344d2640105367f967c33713f9:2515242,005c4e7ccfa240108202aaded9ddfee2:-1460202391</update_guid_history>
    </sys_update_version>
    <sys_metadata_delete action="INSERT_OR_UPDATE">
        <sys_audit_delete/>
        <sys_class_name>sys_metadata_delete</sys_class_name>
        <sys_created_by>admin</sys_created_by>
        <sys_created_on>2020-01-22 13:37:40</sys_created_on>
        <sys_db_object display_value="" name="sys_choice_set">sys_choice_set</sys_db_object>
        <sys_id>8656ee342f264010b634811df699b6c2</sys_id>
        <sys_metadata>8656ee342f264010b634811df699b6c2</sys_metadata>
        <sys_mod_count>0</sys_mod_count>
        <sys_name>u_what_needed</sys_name>
        <sys_package display_value="NeedIt" source="x_58872_needit">6ead8e780f603200cd674f8ce1050ed1</sys_package>
        <sys_parent/>
        <sys_policy/>
        <sys_scope display_value="NeedIt">6ead8e780f603200cd674f8ce1050ed1</sys_scope>
        <sys_scope_delete display_value="">94872a8897db403e8ee69a431de2fca4</sys_scope_delete>
        <sys_update_name>sys_choice_x_58872_needit_needit_u_what_needed</sys_update_name>
        <sys_update_version display_value="sys_choice_x_58872_needit_needit_u_what_needed">3456ae342f264010b634811df699b610</sys_update_version>
        <sys_updated_by>admin</sys_updated_by>
        <sys_updated_on>2020-01-22 13:37:40</sys_updated_on>
    </sys_metadata_delete>
</record_update>
